MANIFEST.in
README.md
setup.py
inPYinting/__init__.py
inPYinting/inpainter.py
inPYinting.egg-info/PKG-INFO
inPYinting.egg-info/SOURCES.txt
inPYinting.egg-info/dependency_links.txt
inPYinting.egg-info/requires.txt
inPYinting.egg-info/top_level.txt
inPYinting/__pycache__/__init__.cpython-38.pyc
inPYinting/__pycache__/inpainter.cpython-38.pyc
inPYinting/algorithms/exemplar_based/exemplar_based_inpainting.py
inPYinting/algorithms/exemplar_based/exemplar_based_utils.py
inPYinting/algorithms/exemplar_based/__pycache__/exemplar_based_inpainting.cpython-38.pyc
inPYinting/algorithms/exemplar_based/__pycache__/exemplar_based_utils.cpython-38.pyc
inPYinting/algorithms/fast_marching/fast_marching_inpainter.py
inPYinting/algorithms/fast_marching/__pycache__/fast_marching_inpainter.cpython-38.pyc
inPYinting/algorithms/navier_stokes/navier_stokes_inpainter.py
inPYinting/algorithms/navier_stokes/__pycache__/navier_stokes_inpainter.cpython-38.pyc
inPYinting/algorithms/pde/amle_inpainter.py
inPYinting/algorithms/pde/cahn_hilliard_inpainter.py
inPYinting/algorithms/pde/harmonic_inpainter.py
inPYinting/algorithms/pde/mumford_shah_inpainter.py
inPYinting/algorithms/pde/transport_inpainting.py
inPYinting/algorithms/pde/__pycache__/amle_inpainter.cpython-38.pyc
inPYinting/algorithms/pde/__pycache__/cahn_hilliard_inpainter.cpython-38.pyc
inPYinting/algorithms/pde/__pycache__/harmonic_inpainter.cpython-38.pyc
inPYinting/algorithms/pde/__pycache__/mumford_shah_inpainter.cpython-38.pyc
inPYinting/algorithms/pde/__pycache__/transport_inpainting.cpython-38.pyc
inPYinting/algorithms/pde/utils/boundary_condition.py
inPYinting/algorithms/pde/utils/derivative_direction.py
inPYinting/algorithms/pde/utils/pde_inpainter.py
inPYinting/algorithms/pde/utils/utils.py
inPYinting/algorithms/pde/utils/__pycache__/boundary_condition.cpython-38.pyc
inPYinting/algorithms/pde/utils/__pycache__/derivative_direction.cpython-38.pyc
inPYinting/algorithms/pde/utils/__pycache__/pde_inpainter.cpython-38.pyc
inPYinting/algorithms/pde/utils/__pycache__/utils.cpython-38.pyc
inPYinting/algorithms/softcolor/softcolor_inpainter.py
