Metadata-Version: 1.0
Name: inPYinting
Version: 1.0
Summary: Set of algorithms for image reconstruction and inpainting
Home-page: https://github.com/mmunar97/inPYinting
Author: marcmunar
Author-email: marc.munar@uib.es
License: mit
Platform: UNKNOWN
